sequana_pipelines/fastqc/__init__.py
sequana_pipelines/fastqc/config.yaml
sequana_pipelines/fastqc/dag.png
sequana_pipelines/fastqc/data/__init__.py
sequana_pipelines/fastqc/fastqc.rules
sequana_pipelines/fastqc/logo.png
sequana_pipelines/fastqc/main.py
sequana_pipelines/fastqc/multiqc_config.yaml
sequana_pipelines/fastqc/schema.yaml
sequana_pipelines/fastqc/tools.txt
sequana_fastqc-1.9.0.dist-info/LICENSE
sequana_fastqc-1.9.0.dist-info/METADATA
sequana_fastqc-1.9.0.dist-info/WHEEL
sequana_fastqc-1.9.0.dist-info/entry_points.txt
sequana_fastqc-1.9.0.dist-info/RECORD
